azure_cis_scanner/azure_cis_scanner.ipynb
azure_cis_scanner/controller.py
azure_cis_scanner/credentials.py
azure_cis_scanner/generate_latex_tables.py
azure_cis_scanner/utils.py
azure_cis_scanner/modules/logging_and_monitoring.py
azure_cis_scanner/modules/networking.py
azure_cis_scanner/modules/other_security_considerations.py
azure_cis_scanner/modules/security_center.py
azure_cis_scanner/modules/sql_servers.py
azure_cis_scanner/modules/storage_accounts.py
azure_cis_scanner/modules/virtual_machines.py
azure_cis_scanner/report/app-test.py
azure_cis_scanner/report/app.py
azure_cis_scanner/report/cis_structure.yaml
azure_cis_scanner/report/manage.py
azure_cis_scanner/report/render_utils.py
azure_cis_scanner/report/settings.py
azure_cis_scanner/report/static/base.css
azure_cis_scanner/report/static/style.css
azure_cis_scanner/report/templates/base.html
azure_cis_scanner/report/templates/finding.html
azure_cis_scanner/report/templates/index.html
azure_cis_scanner/report/templates/service.html
azure_cis_scanner/report/templates/site.html
azure_cis_scanner/tests/test_notes.py
azure_cis_scanner-0.3.5.data/scripts/azscan
azure_cis_scanner-0.3.5.dist-info/DESCRIPTION.rst
azure_cis_scanner-0.3.5.dist-info/METADATA
azure_cis_scanner-0.3.5.dist-info/RECORD
azure_cis_scanner-0.3.5.dist-info/WHEEL
azure_cis_scanner-0.3.5.dist-info/entry_points.txt
azure_cis_scanner-0.3.5.dist-info/metadata.json
azure_cis_scanner-0.3.5.dist-info/top_level.txt
