Metadata-Version: 2.0
Name: azure-cis-scanner
Version: 0.3.5
Summary: Azure CIS Scanner for security
Home-page: https://github.com/praetorian-inc/azure_cis_scanner
Author: kesten broughton, tanner harper
Author-email: kesten.broughton@praetorian.com
License: GNU General Public License v2 (GPLv2)
Platform: UNKNOWN
Classifier: Development Status :: 3 - Alpha
Classifier: Intended Audience :: Developers
Classifier: Intended Audience :: Information Technology
Classifier: Intended Audience :: System Administrators
Classifier: Natural Language :: English
Classifier: License :: OSI Approved :: GNU General Public License v2 (GPLv2)
Classifier: Programming Language :: Python
Classifier: Programming Language :: Python :: 3.6
Requires-Dist: requests
Requires-Dist: pyyaml
Requires-Dist: run-jnb
Requires-Dist: nbstripout
Requires-Dist: numpy
Requires-Dist: pandas
Requires-Dist: matplotlib
Requires-Dist: flask
Requires-Dist: flask-nav
Requires-Dist: azure-storage-blob
Requires-Dist: azure-storage-queue
Requires-Dist: azure-storage-file
Requires-Dist: azure-graphrbac
Requires-Dist: azure-keyvault
Requires-Dist: azure-mgmt-authorization
Requires-Dist: azure-mgmt-billing
Requires-Dist: azure-mgmt-compute
Requires-Dist: azure-mgmt-keyvault
Requires-Dist: azure-mgmt-loganalytics
Requires-Dist: azure-mgmt-managementgroups
Requires-Dist: azure-mgmt-monitor
Requires-Dist: azure-mgmt-msi
Requires-Dist: azure-mgmt-network
Requires-Dist: azure-mgmt-notificationhubs
Requires-Dist: azure-mgmt-policyinsights
Requires-Dist: azure-mgmt-rdbms
Requires-Dist: azure-mgmt-recoveryservices
Requires-Dist: azure-mgmt-recoveryservicesbackup
Requires-Dist: azure-mgmt-resource
Requires-Dist: azure-mgmt-sql
Requires-Dist: azure-mgmt-storage
Requires-Dist: azure-mgmt-subscription
Requires-Dist: azure-cli-core
Requires-Dist: azurerm
